[
    {
        "id": 1,
        "type": "منحة",
        "title": "منحة الملك سلمان للابتعاث",
        "description": "منحة دراسية كاملة لدراسة البكالوريوس والماجستير في أفضل الجامعات العالمية. تشمل الرسوم الدراسية والسكن والتأمين الصحي.",
        "organization": "وزارة التعليم السعودية",
        "deadline": "2026-09-30",
        "eligibility": "معدل لا يقل عن 85% في الثانوية العامة",
        "link": "https://example.com/scholarship1"
    },
    {
        "id": 2,
        "type": "منحة",
        "title": "منحة الأمم المتحدة للتنمية المستدامة",
        "description": "برنامج منح لدعم الباحثين في مجالات الطاقة المتجددة والاستدامة البيئية. تغطي المنحة تكاليف البحث والإقامة لمدة عامين.",
        "organization": "UNDP",
        "deadline": "2026-08-15",
        "eligibility": "حاصل على درجة الماجستير في تخصص ذي صلة",
        "link": "https://example.com/scholarship2"
    },
    {
        "id": 3,
        "type": "منحة",
        "title": "منحة مؤسسة محمد بن راشد آل مكتوم",
        "description": "منحة للتميز الأكاديمي في مجالات العلوم والتكنولوجيا والهندسة والرياضيات (STEM) للطلاب العرب.",
        "organization": "مؤسسة محمد بن راشد آل مكتوم",
        "deadline": "2026-10-01",
        "eligibility": "طلاب الجامعات العربية بمعدل تراكمي لا يقل عن 3.5",
        "link": "https://example.com/scholarship3"
    },
    {
        "id": 4,
        "type": "منحة",
        "title": "منحة تشيفنينغ البريطانية",
        "description": "منحة حكومية بريطانية للقادة الطموحين لدراسة الماجستير في المملكة المتحدة. تغطي الرسوم الدراسية وتذاكر الطيران والمعيشة.",
        "organization": "الحكومة البريطانية",
        "deadline": "2026-11-01",
        "eligibility": "خبرة مهنية لا تقل عن سنتين",
        "link": "https://example.com/scholarship4"
    },
    {
        "id": 5,
        "type": "منحة",
        "title": "برنامج فولبرايت للتبادل الثقافي",
        "description": "منحة تبادل ثقافي وأكاديمي للطلاب والخريجين الجدد للدراسة والبحث في الولايات المتحدة الأمريكية.",
        "organization": "اللجنة الأمريكية للتبادل الثقافي",
        "deadline": "2026-07-30",
        "eligibility": "إجادة اللغة الإنجليزية (TOEFL 80+)",
        "link": "https://example.com/scholarship5"
    },
    {
        "id": 6,
        "type": "منحة",
        "title": "منحة DAAD الألمانية للدراسات العليا",
        "description": "منحة كاملة من هيئة التبادل الأكاديمي الألمانية لدراسة الماجستير والدكتوراه في الجامعات الألمانية.",
        "organization": "DAAD",
        "deadline": "2026-09-15",
        "eligibility": "بكالوريوس بمعدل جيد جداً على الأقل",
        "link": "https://example.com/scholarship6"
    },
    {
        "id": 7,
        "type": "وظيفة",
        "title": "مهندس طاقة متجددة",
        "description": "مطلوب مهندس طاقة متجددة للعمل على مشاريع الطاقة الشمسية والرياح. يشمل التصميم والتنفيذ والصيانة.",
        "organization": "شركة الخضراء للطاقة",
        "deadline": "2026-07-15",
        "eligibility": "بكالوريوس هندسة طاقة أو كهرباء، خبرة سنتين",
        "link": "https://example.com/job1"
    },
    {
        "id": 8,
        "type": "وظيفة",
        "title": "محلل نظم أمن معلومات",
        "description": "البحث عن محلل أمن سيبراني لحماية البنية التحتية الرقمية للمنصة. يشمل اختبار الاختراق وإدارة الثغرات.",
        "organization": "فرص خضراء",
        "deadline": "2026-08-01",
        "eligibility": "شهادة في أمن المعلومات أو خبرة مماثلة",
        "link": "https://example.com/job2"
    },
    {
        "id": 9,
        "type": "وظيفة",
        "title": "مستشار بيئي",
        "description": "تقديم استشارات للمؤسسات حول الامتثال البيئي وتقييم الأثر البيئي للمشاريع الجديدة.",
        "organization": "الاستشارات الخضراء المتحدة",
        "deadline": "2026-07-30",
        "eligibility": "ماجستير في العلوم البيئية، خبرة 3 سنوات",
        "link": "https://example.com/job3"
    },
    {
        "id": 10,
        "type": "وظيفة",
        "title": "مطور واجهات أمامية",
        "description": "تطوير واجهات مستخدم تفاعلية لمنصة الفرص الرقمية باستخدام React و JavaScript.",
        "organization": "فرص خضراء",
        "deadline": "2026-08-15",
        "eligibility": "خبرة سنتين في React وتقنيات الويب",
        "link": "https://example.com/job4"
    },
    {
        "id": 11,
        "type": "وظيفة",
        "title": "مدير مشاريع استدامة",
        "description": "إدارة وتنسيق مشاريع الاستدامة البيئية في القطاع الخاص. يشمل إعداد التقارير ومتابعة المؤشرات.",
        "organization": "مجموعة الخليج الأخضر",
        "deadline": "2026-09-01",
        "eligibility": "خبرة 5 سنوات في إدارة المشاريع، PMP مفضل",
        "link": "https://example.com/job5"
    },
    {
        "id": 12,
        "type": "وظيفة",
        "title": "أخصائي تسويق رقمي",
        "description": "إدارة الحملات التسويقية لمنصة الفرص عبر وسائل التواصل الاجتماعي والبريد الإلكتروني.",
        "organization": "فرص خضراء",
        "deadline": "2026-07-20",
        "eligibility": "خبرة في التسويق الرقمي وإدارة السوشيال ميديا",
        "link": "https://example.com/job6"
    },
    {
        "id": 13,
        "type": "تدريب",
        "title": "برنامج تدريب الأمن السيبراني",
        "description": "برنامج تدريبي مكثف لمدة 6 أشهر في مجال الأمن السيبراني يشمل اختبار الاختراق والدفاع الرقمي وتحليل الثغرات.",
        "organization": "أكاديمية الأمن الرقمي",
        "deadline": "2026-08-01",
        "eligibility": "خريج تقنية معلومات أو طالب في سنة أخيرة",
        "link": "https://example.com/training1"
    },
    {
        "id": 14,
        "type": "تدريب",
        "title": "برنامج تدريب الطاقة الشمسية",
        "description": "دورة تدريبية عملية في تركيب وصيانة أنظمة الطاقة الشمسية للمنازل والمنشآت الصغيرة.",
        "organization": "مركز التدريب الأخضر",
        "deadline": "2026-07-25",
        "eligibility": "شهادة ثانوية عامة، لا يشترط خبرة سابقة",
        "link": "https://example.com/training2"
    },
    {
        "id": 15,
        "type": "تدريب",
        "title": "مهارات القيادة للاستدامة",
        "description": "برنامج تدريبي لتطوير مهارات القيادة في مجال الاستدامة البيئية والمسؤولية المجتمعية للشركات.",
        "organization": "منتدى القيادة الخضراء",
        "deadline": "2026-09-10",
        "eligibility": "خبرة إدارية لا تقل عن 3 سنوات",
        "link": "https://example.com/training3"
    },
    {
        "id": 16,
        "type": "تدريب",
        "title": "دورة تطوير تطبيقات الذكاء الاصطناعي",
        "description": "دورة تدريبية متقدمة في بناء تطبيقات الذكاء الاصطناعي باستخدام Python و机器学习.",
        "organization": "معهد التقنيات الحديثة",
        "deadline": "2026-08-20",
        "eligibility": "معرفة أساسية في Python",
        "link": "https://example.com/training4"
    },
    {
        "id": 17,
        "type": "تدريب",
        "title": "برنامج الإدارة البيئية المتكاملة",
        "description": "تدريب مهني معتمد في أنظمة الإدارة البيئية ISO 14001 وتقييم دورة الحياة.",
        "organization": "الغرفة التجارية الخضراء",
        "deadline": "2026-10-01",
        "eligibility": "موظف في قطاع البيئة أو الصحة والسلامة",
        "link": "https://example.com/training5"
    },
    {
        "id": 18,
        "type": "تدريب",
        "title": "ورشة كتابة السيرة الذاتية والمقابلات",
        "description": "ورشة عمل مجانية لتطوير مهارات كتابة السيرة الذاتية والاستعداد لمقابلات العمل.",
        "organization": "فرص خضراء",
        "deadline": "2026-07-10",
        "eligibility": "مفتوح للجميع",
        "link": "https://example.com/training6"
    }
]
